apprentice/__init__.py
apprentice/approximationbase.py
apprentice/appset.py
apprentice/io.py
apprentice/monomial.py
apprentice/onb.py
apprentice/ortho.py
apprentice/polynomialapproximation.py
apprentice/rationalapproximation.py
apprentice/rationalapproximationONB.py
apprentice/rationalapproximationONBtest.py
apprentice/rationalapproximationSIP.py
apprentice/rationalapproximationSIPONB.py
apprentice/rationalapproximationSLSQP.py
apprentice/scaler.py
apprentice/testData.py
apprentice/tools.py
apprentice/weights.py
pyapprentice-1.0.6.data/scripts/app-build
pyapprentice-1.0.6.data/scripts/app-datadirtojson
pyapprentice-1.0.6.data/scripts/app-ls
pyapprentice-1.0.6.data/scripts/app-nest
pyapprentice-1.0.6.data/scripts/app-predict
pyapprentice-1.0.6.data/scripts/app-rox
pyapprentice-1.0.6.data/scripts/app-rox-parallel
pyapprentice-1.0.6.data/scripts/app-sample
pyapprentice-1.0.6.data/scripts/app-tune
pyapprentice-1.0.6.data/scripts/app-tune2
pyapprentice-1.0.6.data/scripts/app-yoda2h5
pyapprentice-1.0.6.data/scripts/app-yodaenvelope
pyapprentice-1.0.6.data/scripts/convert.py
pyapprentice-1.0.6.data/scripts/convertData.py
pyapprentice-1.0.6.data/scripts/extrema.py
pyapprentice-1.0.6.data/scripts/simplecomp.py
pyapprentice-1.0.6.dist-info/LICENSE
pyapprentice-1.0.6.dist-info/METADATA
pyapprentice-1.0.6.dist-info/WHEEL
pyapprentice-1.0.6.dist-info/top_level.txt
pyapprentice-1.0.6.dist-info/RECORD
