Metadata-Version: 2.1
Name: pyapprentice
Version: 1.0.6
Summary: The apprentice
Home-page: https://computing.fnal.gov/hep-on-hpc/
Author: Mohan Krishnamoorthy, Holger Schulz
Author-email: mkrishnamoorthy@anl.gov, iamholger@gmail.com
License: UNKNOWN
Platform: UNKNOWN
Requires-Dist: numpy (>=1.15.0)
Requires-Dist: scipy (>=1.3.0)
Requires-Dist: sklearn
Requires-Dist: numba (>=0.40.0)
Requires-Dist: h5py (>=2.8.0)
Requires-Dist: mpi4py (>=3.0.0)
Requires-Dist: matplotlib (>=3.0.0)
Requires-Dist: pyDOE2 (>=1.3.0)
